<?xml version="1.0" encoding="UTF-8" standalone="no"?>
<XMI xmlns:UML="omg.org/UML1.3" xmi.version="1.1">
    <XMI.header>
        <XMI.documentation>
            <XMI.exporter>Enterprise Architect</XMI.exporter>
            <XMI.exporterVersion>2.5</XMI.exporterVersion>
        </XMI.documentation>
    </XMI.header>
    <XMI.content>
        <UML:Model name="EA Model" xmi.id="MX_EAID_90017535_4279_8162_2822_381163394359">
            <UML:Namespace.ownedElement>
                <UML:Class name="EARootClass" xmi.id="EAID_70273504_3452_9025_1905_848212386994"/>
                <UML:Package name="One Level Block Hierarchy" xmi.id="EAPK_30494558_2566_9176_5511_514611744827">
                    <UML:Namespace.ownedElement>
                        <UML:Class name="FGS" namespace="EAPK_30494558_2566_9176_5511_514611744827" xmi.id="EAID_42650654_9738_5473_4177_718982955281">
                            <UML:ModelElement.stereotype>
                                <UML:Stereotype name="block"/>
                            </UML:ModelElement.stereotype>
                            <UML:ModelElement.taggedValue>
                                <UML:TaggedValue tag="ea_stype" value="Class"/>
                                <UML:TaggedValue tag="package" value="EAPK_30494558_2566_9176_5511_514611744827"/>
                                <UML:TaggedValue tag="package_name" value="One Level Block Hierarchy"/>
                                <UML:TaggedValue tag="stereotype" value="block"/>
                            </UML:ModelElement.taggedValue>
                        </UML:Class>
                        <UML:Class name="BUS" namespace="EAPK_30494558_2566_9176_5511_514611744827" xmi.id="EAID_47333264_1216_2617_4382_771395273610">
                            <UML:ModelElement.stereotype>
                                <UML:Stereotype name="block"/>
                            </UML:ModelElement.stereotype>
                            <UML:ModelElement.taggedValue>
                                <UML:TaggedValue tag="ea_stype" value="Class"/>
                                <UML:TaggedValue tag="package" value="EAPK_30494558_2566_9176_5511_514611744827"/>
                                <UML:TaggedValue tag="package_name" value="One Level Block Hierarchy"/>
                                <UML:TaggedValue tag="stereotype" value="block"/>
                            </UML:ModelElement.taggedValue>
                        </UML:Class>
                        <UML:Class name="FCS" namespace="EAPK_30494558_2566_9176_5511_514611744827" xmi.id="EAID_92984298_1855_2127_1284_294648102216">
                            <UML:ModelElement.stereotype>
                                <UML:Stereotype name="block"/>
                            </UML:ModelElement.stereotype>
                            <UML:ModelElement.taggedValue>
                                <UML:TaggedValue tag="ea_stype" value="Class"/>
                                <UML:TaggedValue tag="package" value="EAPK_30494558_2566_9176_5511_514611744827"/>
                                <UML:TaggedValue tag="package_name" value="One Level Block Hierarchy"/>
                                <UML:TaggedValue tag="stereotype" value="block"/>
                                <UML:TaggedValue tag="diagram" value="EAID_43130174_8573_8075_2473_503365140897"/>
                            </UML:ModelElement.taggedValue>
                        </UML:Class>
                        <UML:Class name="PRIMARY_SIDE" namespace="EAPK_30494558_2566_9176_5511_514611744827" xmi.id="EAID_63056512_6562_9130_3480_502808193680">
                            <UML:ModelElement.taggedValue>
                                <UML:TaggedValue tag="ea_stype" value="Port"/>
                                <UML:TaggedValue tag="package" value="EAPK_30494558_2566_9176_5511_514611744827"/>
                                <UML:TaggedValue tag="owner" value="EAID_92984298_1855_2127_1284_294648102216"/>
                                <UML:TaggedValue tag="package_name" value="One Level Block Hierarchy"/>
                            </UML:ModelElement.taggedValue>
                        </UML:Class>
                        <UML:Class name="TRANSFER_SWITCH" namespace="EAPK_30494558_2566_9176_5511_514611744827" xmi.id="EAID_62321814_7253_5752_8551_113955679121">
                            <UML:ModelElement.taggedValue>
                                <UML:TaggedValue tag="ea_stype" value="Port"/>
                                <UML:TaggedValue tag="package" value="EAPK_30494558_2566_9176_5511_514611744827"/>
                                <UML:TaggedValue tag="owner" value="EAID_92984298_1855_2127_1284_294648102216"/>
                                <UML:TaggedValue tag="package_name" value="One Level Block Hierarchy"/>
                            </UML:ModelElement.taggedValue>
                        </UML:Class>
                        <UML:Class name="BUS_IN" namespace="EAPK_30494558_2566_9176_5511_514611744827" xmi.id="EAID_35789767_5738_6705_3211_666834836315">
                            <UML:ModelElement.taggedValue>
                                <UML:TaggedValue tag="ea_stype" value="Port"/>
                                <UML:TaggedValue tag="package" value="EAPK_30494558_2566_9176_5511_514611744827"/>
                                <UML:TaggedValue tag="owner" value="EAID_42650654_9738_5473_4177_718982955281"/>
                                <UML:TaggedValue tag="package_name" value="One Level Block Hierarchy"/>
                            </UML:ModelElement.taggedValue>
                        </UML:Class>
                        <UML:Class name="CLK" namespace="EAPK_30494558_2566_9176_5511_514611744827" xmi.id="EAID_92402114_5900_9402_6879_646260384548">
                            <UML:ModelElement.taggedValue>
                                <UML:TaggedValue tag="ea_stype" value="Port"/>
                                <UML:TaggedValue tag="package" value="EAPK_30494558_2566_9176_5511_514611744827"/>
                                <UML:TaggedValue tag="owner" value="EAID_42650654_9738_5473_4177_718982955281"/>
                                <UML:TaggedValue tag="package_name" value="One Level Block Hierarchy"/>
                            </UML:ModelElement.taggedValue>
                        </UML:Class>
                        <UML:Class name="PILOT_FLYING" namespace="EAPK_30494558_2566_9176_5511_514611744827" xmi.id="EAID_78492781_2296_5292_6326_969686845577">
                            <UML:ModelElement.taggedValue>
                                <UML:TaggedValue tag="ea_stype" value="Port"/>
                                <UML:TaggedValue tag="package" value="EAPK_30494558_2566_9176_5511_514611744827"/>
                                <UML:TaggedValue tag="owner" value="EAID_42650654_9738_5473_4177_718982955281"/>
                                <UML:TaggedValue tag="package_name" value="One Level Block Hierarchy"/>
                            </UML:ModelElement.taggedValue>
                        </UML:Class>
                        <UML:Class name="PRIMARY_SIDE" namespace="EAPK_30494558_2566_9176_5511_514611744827" xmi.id="EAID_72550204_3615_8175_8303_354971874703">
                            <UML:ModelElement.taggedValue>
                                <UML:TaggedValue tag="ea_stype" value="Port"/>
                                <UML:TaggedValue tag="package" value="EAPK_30494558_2566_9176_5511_514611744827"/>
                                <UML:TaggedValue tag="owner" value="EAID_42650654_9738_5473_4177_718982955281"/>
                                <UML:TaggedValue tag="package_name" value="One Level Block Hierarchy"/>
                            </UML:ModelElement.taggedValue>
                        </UML:Class>
                        <UML:Class name="TRANSFER_SWITCH" namespace="EAPK_30494558_2566_9176_5511_514611744827" xmi.id="EAID_43633111_1320_2944_5067_705911547494">
                            <UML:ModelElement.taggedValue>
                                <UML:TaggedValue tag="ea_stype" value="Port"/>
                                <UML:TaggedValue tag="package" value="EAPK_30494558_2566_9176_5511_514611744827"/>
                                <UML:TaggedValue tag="owner" value="EAID_42650654_9738_5473_4177_718982955281"/>
                                <UML:TaggedValue tag="package_name" value="One Level Block Hierarchy"/>
                            </UML:ModelElement.taggedValue>
                        </UML:Class>
                        <UML:Class name="RIGHT" namespace="EAPK_30494558_2566_9176_5511_514611744827" xmi.id="EAID_72721734_6950_2850_4835_415330318614">
                            <UML:ModelElement.taggedValue>
                                <UML:TaggedValue tag="ea_stype" value="Port"/>
                                <UML:TaggedValue tag="package" value="EAPK_30494558_2566_9176_5511_514611744827"/>
                                <UML:TaggedValue tag="owner" value="EAID_47333264_1216_2617_4382_771395273610"/>
                                <UML:TaggedValue tag="package_name" value="One Level Block Hierarchy"/>
                            </UML:ModelElement.taggedValue>
                        </UML:Class>
                        <UML:Class name="CLK" namespace="EAPK_30494558_2566_9176_5511_514611744827" xmi.id="EAID_45157353_1566_9797_4543_452208450746">
                            <UML:ModelElement.taggedValue>
                                <UML:TaggedValue tag="ea_stype" value="Port"/>
                                <UML:TaggedValue tag="package" value="EAPK_30494558_2566_9176_5511_514611744827"/>
                                <UML:TaggedValue tag="owner" value="EAID_47333264_1216_2617_4382_771395273610"/>
                                <UML:TaggedValue tag="package_name" value="One Level Block Hierarchy"/>
                            </UML:ModelElement.taggedValue>
                        </UML:Class>
                        <UML:Class name="LEFT" namespace="EAPK_30494558_2566_9176_5511_514611744827" xmi.id="EAID_97287088_9646_9394_8128_536388273418">
                            <UML:ModelElement.taggedValue>
                                <UML:TaggedValue tag="ea_stype" value="Port"/>
                                <UML:TaggedValue tag="package" value="EAPK_30494558_2566_9176_5511_514611744827"/>
                                <UML:TaggedValue tag="owner" value="EAID_47333264_1216_2617_4382_771395273610"/>
                                <UML:TaggedValue tag="package_name" value="One Level Block Hierarchy"/>
                            </UML:ModelElement.taggedValue>
                        </UML:Class>
                        <UML:Collaboration name="Collaborations" xmi.id="EAID_90017535_4279_8162_2822_381163394359_Collaboration">
                            <UML:Collaboration.interaction/>
                            <UML:Namespace.ownedElement>
                                <UML:ClassifierRole base="EAID_70273504_3452_9025_1905_848212386994" name="LEFT_SIDE" xmi.id="EAID_12588843_2119_6794_9583_108364758766">
                                    <UML:ModelElement.taggedValue>
                                        <UML:TaggedValue tag="ea_stype" value="Part"/>
                                        <UML:TaggedValue tag="package" value="EAPK_30494558_2566_9176_5511_514611744827"/>
                                        <UML:TaggedValue tag="owner" value="EAID_42650654_9738_5473_4177_718982955281"/>
                                        <UML:TaggedValue tag="package_name" value="One Level Block Hierarchy"/>
                                        <UML:TaggedValue tag="propertyType" value="{42650654-9738-5473-4177-718982955281}"/>
                                    </UML:ModelElement.taggedValue>
                                </UML:ClassifierRole>
                                <UML:ClassifierRole base="EAID_70273504_3452_9025_1905_848212386994" name="RIGHT_SIDE" xmi.id="EAID_18913292_7041_9246_3127_995479321146">
                                    <UML:ModelElement.taggedValue>
                                        <UML:TaggedValue tag="ea_stype" value="Part"/>
                                        <UML:TaggedValue tag="package" value="EAPK_30494558_2566_9176_5511_514611744827"/>
                                        <UML:TaggedValue tag="owner" value="EAID_42650654_9738_5473_4177_718982955281"/>
                                        <UML:TaggedValue tag="package_name" value="One Level Block Hierarchy"/>
                                        <UML:TaggedValue tag="propertyType" value="{42650654-9738-5473-4177-718982955281}"/>
                                    </UML:ModelElement.taggedValue>
                                </UML:ClassifierRole>
                                <UML:ClassifierRole base="EAID_70273504_3452_9025_1905_848212386994" name="LR" xmi.id="EAID_47176645_1928_8006_5407_972225358555">
                                    <UML:ModelElement.taggedValue>
                                        <UML:TaggedValue tag="ea_stype" value="Part"/>
                                        <UML:TaggedValue tag="package" value="EAPK_30494558_2566_9176_5511_514611744827"/>
                                        <UML:TaggedValue tag="owner" value="EAID_47333264_1216_2617_4382_771395273610"/>
                                        <UML:TaggedValue tag="package_name" value="One Level Block Hierarchy"/>
                                        <UML:TaggedValue tag="propertyType" value="{47333264-1216-2617-4382-771395273610}"/>
                                    </UML:ModelElement.taggedValue>
                                </UML:ClassifierRole>
                                <UML:ClassifierRole base="EAID_70273504_3452_9025_1905_848212386994" name="RL" xmi.id="EAID_16176098_5148_2296_2967_104075413716">
                                    <UML:ModelElement.taggedValue>
                                        <UML:TaggedValue tag="ea_stype" value="Part"/>
                                        <UML:TaggedValue tag="package" value="EAPK_30494558_2566_9176_5511_514611744827"/>
                                        <UML:TaggedValue tag="owner" value="EAID_47333264_1216_2617_4382_771395273610"/>
                                        <UML:TaggedValue tag="package_name" value="One Level Block Hierarchy"/>
                                        <UML:TaggedValue tag="propertyType" value="{47333264-1216-2617-4382-771395273610}"/>
                                    </UML:ModelElement.taggedValue>
                                </UML:ClassifierRole>
                            </UML:Namespace.ownedElement>
                        </UML:Collaboration>
                        <UML:Class name="BUS_IN" namespace="EAPK_30494558_2566_9176_5511_514611744827" xmi.id="EAID_26893162_1009_5954_2311_332999979623">
                            <UML:ModelElement.taggedValue>
                                <UML:TaggedValue tag="ea_stype" value="Port"/>
                                <UML:TaggedValue tag="package" value="EAPK_30494558_2566_9176_5511_514611744827"/>
                                <UML:TaggedValue tag="owner" value="EAID_12588843_2119_6794_9583_108364758766"/>
                                <UML:TaggedValue tag="package_name" value="One Level Block Hierarchy"/>
                                <UML:TaggedValue tag="reusesProperty" value="{35789767-5738-6705-3211-666834836315}"/>
                            </UML:ModelElement.taggedValue>
                        </UML:Class>
                        <UML:Class name="CLK" namespace="EAPK_30494558_2566_9176_5511_514611744827" xmi.id="EAID_40089394_1448_6739_5748_907946359794">
                            <UML:ModelElement.taggedValue>
                                <UML:TaggedValue tag="ea_stype" value="Port"/>
                                <UML:TaggedValue tag="package" value="EAPK_30494558_2566_9176_5511_514611744827"/>
                                <UML:TaggedValue tag="owner" value="EAID_12588843_2119_6794_9583_108364758766"/>
                                <UML:TaggedValue tag="package_name" value="One Level Block Hierarchy"/>
                                <UML:TaggedValue tag="reusesProperty" value="{92402114-5900-9402-6879-646260384548}"/>
                            </UML:ModelElement.taggedValue>
                        </UML:Class>
                        <UML:Class name="PILOT_FLYING" namespace="EAPK_30494558_2566_9176_5511_514611744827" xmi.id="EAID_12702060_6825_5470_5816_870500770863">
                            <UML:ModelElement.taggedValue>
                                <UML:TaggedValue tag="ea_stype" value="Port"/>
                                <UML:TaggedValue tag="package" value="EAPK_30494558_2566_9176_5511_514611744827"/>
                                <UML:TaggedValue tag="owner" value="EAID_12588843_2119_6794_9583_108364758766"/>
                                <UML:TaggedValue tag="package_name" value="One Level Block Hierarchy"/>
                                <UML:TaggedValue tag="reusesProperty" value="{78492781-2296-5292-6326-969686845577}"/>
                            </UML:ModelElement.taggedValue>
                        </UML:Class>
                        <UML:Class name="PRIMARY_SIDE" namespace="EAPK_30494558_2566_9176_5511_514611744827" xmi.id="EAID_91752754_8824_1399_8305_902131435515">
                            <UML:ModelElement.taggedValue>
                                <UML:TaggedValue tag="ea_stype" value="Port"/>
                                <UML:TaggedValue tag="package" value="EAPK_30494558_2566_9176_5511_514611744827"/>
                                <UML:TaggedValue tag="owner" value="EAID_12588843_2119_6794_9583_108364758766"/>
                                <UML:TaggedValue tag="package_name" value="One Level Block Hierarchy"/>
                                <UML:TaggedValue tag="reusesProperty" value="{72550204-3615-8175-8303-354971874703}"/>
                            </UML:ModelElement.taggedValue>
                        </UML:Class>
                        <UML:Class name="TRANSFER_SWITCH" namespace="EAPK_30494558_2566_9176_5511_514611744827" xmi.id="EAID_27649737_4131_4757_6316_827709435040">
                            <UML:ModelElement.taggedValue>
                                <UML:TaggedValue tag="ea_stype" value="Port"/>
                                <UML:TaggedValue tag="package" value="EAPK_30494558_2566_9176_5511_514611744827"/>
                                <UML:TaggedValue tag="owner" value="EAID_12588843_2119_6794_9583_108364758766"/>
                                <UML:TaggedValue tag="package_name" value="One Level Block Hierarchy"/>
                                <UML:TaggedValue tag="reusesProperty" value="{43633111-1320-2944-5067-705911547494}"/>
                            </UML:ModelElement.taggedValue>
                        </UML:Class>
                        <UML:Class name="BUS_IN" namespace="EAPK_30494558_2566_9176_5511_514611744827" xmi.id="EAID_64511351_7485_2307_3890_910827545249">
                            <UML:ModelElement.taggedValue>
                                <UML:TaggedValue tag="ea_stype" value="Port"/>
                                <UML:TaggedValue tag="package" value="EAPK_30494558_2566_9176_5511_514611744827"/>
                                <UML:TaggedValue tag="owner" value="EAID_18913292_7041_9246_3127_995479321146"/>
                                <UML:TaggedValue tag="package_name" value="One Level Block Hierarchy"/>
                                <UML:TaggedValue tag="reusesProperty" value="{35789767-5738-6705-3211-666834836315}"/>
                            </UML:ModelElement.taggedValue>
                        </UML:Class>
                        <UML:Class name="CLK" namespace="EAPK_30494558_2566_9176_5511_514611744827" xmi.id="EAID_82509287_3546_7046_7842_138363915121">
                            <UML:ModelElement.taggedValue>
                                <UML:TaggedValue tag="ea_stype" value="Port"/>
                                <UML:TaggedValue tag="package" value="EAPK_30494558_2566_9176_5511_514611744827"/>
                                <UML:TaggedValue tag="owner" value="EAID_18913292_7041_9246_3127_995479321146"/>
                                <UML:TaggedValue tag="package_name" value="One Level Block Hierarchy"/>
                                <UML:TaggedValue tag="reusesProperty" value="{92402114-5900-9402-6879-646260384548}"/>
                            </UML:ModelElement.taggedValue>
                        </UML:Class>
                        <UML:Class name="PILOT_FLYING" namespace="EAPK_30494558_2566_9176_5511_514611744827" xmi.id="EAID_37758531_2478_7907_6323_354908967151">
                            <UML:ModelElement.taggedValue>
                                <UML:TaggedValue tag="ea_stype" value="Port"/>
                                <UML:TaggedValue tag="package" value="EAPK_30494558_2566_9176_5511_514611744827"/>
                                <UML:TaggedValue tag="owner" value="EAID_18913292_7041_9246_3127_995479321146"/>
                                <UML:TaggedValue tag="package_name" value="One Level Block Hierarchy"/>
                                <UML:TaggedValue tag="reusesProperty" value="{78492781-2296-5292-6326-969686845577}"/>
                            </UML:ModelElement.taggedValue>
                        </UML:Class>
                        <UML:Class name="PRIMARY_SIDE" namespace="EAPK_30494558_2566_9176_5511_514611744827" xmi.id="EAID_30392826_5149_2174_8662_132240733259">
                            <UML:ModelElement.taggedValue>
                                <UML:TaggedValue tag="ea_stype" value="Port"/>
                                <UML:TaggedValue tag="package" value="EAPK_30494558_2566_9176_5511_514611744827"/>
                                <UML:TaggedValue tag="owner" value="EAID_18913292_7041_9246_3127_995479321146"/>
                                <UML:TaggedValue tag="package_name" value="One Level Block Hierarchy"/>
                                <UML:TaggedValue tag="reusesProperty" value="{72550204-3615-8175-8303-354971874703}"/>
                            </UML:ModelElement.taggedValue>
                        </UML:Class>
                        <UML:Class name="TRANSFER_SWITCH" namespace="EAPK_30494558_2566_9176_5511_514611744827" xmi.id="EAID_69380472_2108_7027_4289_352595488414">
                            <UML:ModelElement.taggedValue>
                                <UML:TaggedValue tag="ea_stype" value="Port"/>
                                <UML:TaggedValue tag="package" value="EAPK_30494558_2566_9176_5511_514611744827"/>
                                <UML:TaggedValue tag="owner" value="EAID_18913292_7041_9246_3127_995479321146"/>
                                <UML:TaggedValue tag="package_name" value="One Level Block Hierarchy"/>
                                <UML:TaggedValue tag="reusesProperty" value="{43633111-1320-2944-5067-705911547494}"/>
                            </UML:ModelElement.taggedValue>
                        </UML:Class>
                        <UML:Class name="RIGHT" namespace="EAPK_30494558_2566_9176_5511_514611744827" xmi.id="EAID_62383181_5076_7775_6410_337631113190">
                            <UML:ModelElement.taggedValue>
                                <UML:TaggedValue tag="ea_stype" value="Port"/>
                                <UML:TaggedValue tag="package" value="EAPK_30494558_2566_9176_5511_514611744827"/>
                                <UML:TaggedValue tag="owner" value="EAID_47176645_1928_8006_5407_972225358555"/>
                                <UML:TaggedValue tag="package_name" value="One Level Block Hierarchy"/>
                                <UML:TaggedValue tag="reusesProperty" value="{72721734-6950-2850-4835-415330318614}"/>
                            </UML:ModelElement.taggedValue>
                        </UML:Class>
                        <UML:Class name="CLK" namespace="EAPK_30494558_2566_9176_5511_514611744827" xmi.id="EAID_44358266_6456_5713_4289_591841327278">
                            <UML:ModelElement.taggedValue>
                                <UML:TaggedValue tag="ea_stype" value="Port"/>
                                <UML:TaggedValue tag="package" value="EAPK_30494558_2566_9176_5511_514611744827"/>
                                <UML:TaggedValue tag="owner" value="EAID_47176645_1928_8006_5407_972225358555"/>
                                <UML:TaggedValue tag="package_name" value="One Level Block Hierarchy"/>
                                <UML:TaggedValue tag="reusesProperty" value="{45157353-1566-9797-4543-452208450746}"/>
                            </UML:ModelElement.taggedValue>
                        </UML:Class>
                        <UML:Class name="LEFT" namespace="EAPK_30494558_2566_9176_5511_514611744827" xmi.id="EAID_43145413_8646_1839_4472_712471442927">
                            <UML:ModelElement.taggedValue>
                                <UML:TaggedValue tag="ea_stype" value="Port"/>
                                <UML:TaggedValue tag="package" value="EAPK_30494558_2566_9176_5511_514611744827"/>
                                <UML:TaggedValue tag="owner" value="EAID_47176645_1928_8006_5407_972225358555"/>
                                <UML:TaggedValue tag="package_name" value="One Level Block Hierarchy"/>
                                <UML:TaggedValue tag="reusesProperty" value="{97287088-9646-9394-8128-536388273418}"/>
                            </UML:ModelElement.taggedValue>
                        </UML:Class>
                        <UML:Class name="RIGHT" namespace="EAPK_30494558_2566_9176_5511_514611744827" xmi.id="EAID_36587005_4617_2656_9841_664002452976">
                            <UML:ModelElement.taggedValue>
                                <UML:TaggedValue tag="ea_stype" value="Port"/>
                                <UML:TaggedValue tag="package" value="EAPK_30494558_2566_9176_5511_514611744827"/>
                                <UML:TaggedValue tag="owner" value="EAID_16176098_5148_2296_2967_104075413716"/>
                                <UML:TaggedValue tag="package_name" value="One Level Block Hierarchy"/>
                                <UML:TaggedValue tag="reusesProperty" value="{72721734-6950-2850-4835-415330318614}"/>
                            </UML:ModelElement.taggedValue>
                        </UML:Class>
                        <UML:Class name="CLK" namespace="EAPK_30494558_2566_9176_5511_514611744827" xmi.id="EAID_86284156_2141_1349_5313_117505446321">
                            <UML:ModelElement.taggedValue>
                                <UML:TaggedValue tag="ea_stype" value="Port"/>
                                <UML:TaggedValue tag="package" value="EAPK_30494558_2566_9176_5511_514611744827"/>
                                <UML:TaggedValue tag="owner" value="EAID_16176098_5148_2296_2967_104075413716"/>
                                <UML:TaggedValue tag="package_name" value="One Level Block Hierarchy"/>
                                <UML:TaggedValue tag="reusesProperty" value="{45157353-1566-9797-4543-452208450746}"/>
                            </UML:ModelElement.taggedValue>
                        </UML:Class>
                        <UML:Class name="LEFT" namespace="EAPK_30494558_2566_9176_5511_514611744827" xmi.id="EAID_86745649_2140_9766_7823_602554421163">
                            <UML:ModelElement.taggedValue>
                                <UML:TaggedValue tag="ea_stype" value="Port"/>
                                <UML:TaggedValue tag="package" value="EAPK_30494558_2566_9176_5511_514611744827"/>
                                <UML:TaggedValue tag="owner" value="EAID_16176098_5148_2296_2967_104075413716"/>
                                <UML:TaggedValue tag="package_name" value="One Level Block Hierarchy"/>
                                <UML:TaggedValue tag="reusesProperty" value="{97287088-9646-9394-8128-536388273418}"/>
                            </UML:ModelElement.taggedValue>
                        </UML:Class>
                        <UML:Association xmi.id="EAID_47422802_6390_6378_4908_493900351156">
                            <UML:ModelElement.taggedValue>
                                <UML:TaggedValue tag="ea_type" value="Connector"/>
                                <UML:TaggedValue tag="direction" value="Source -&amp;gt; Destination"/>
                                <UML:TaggedValue tag="ea_sourceName" value="PILOT_FLYING"/>
                                <UML:TaggedValue tag="ea_targetName" value="LEFT"/>
                                <UML:TaggedValue tag="ea_sourceType" value="Port"/>
                                <UML:TaggedValue tag="ea_targetType" value="Port"/>
                            </UML:ModelElement.taggedValue>
                            <UML:Association.connection>
                                <UML:AssociationEnd type="EAID_12702060_6825_5470_5816_870500770863"/>
                                <UML:AssociationEnd type="EAID_43145413_8646_1839_4472_712471442927"/>
                            </UML:Association.connection>
                        </UML:Association>
                        <UML:Association xmi.id="EAID_10887462_4740_1021_1921_403884633535">
                            <UML:ModelElement.taggedValue>
                                <UML:TaggedValue tag="ea_type" value="Connector"/>
                                <UML:TaggedValue tag="direction" value="Source -&amp;gt; Destination"/>
                                <UML:TaggedValue tag="ea_sourceName" value="LEFT"/>
                                <UML:TaggedValue tag="ea_targetName" value="BUS_IN"/>
                                <UML:TaggedValue tag="ea_sourceType" value="Port"/>
                                <UML:TaggedValue tag="ea_targetType" value="Port"/>
                            </UML:ModelElement.taggedValue>
                            <UML:Association.connection>
                                <UML:AssociationEnd type="EAID_86745649_2140_9766_7823_602554421163"/>
                                <UML:AssociationEnd type="EAID_26893162_1009_5954_2311_332999979623"/>
                            </UML:Association.connection>
                        </UML:Association>
                        <UML:Association xmi.id="EAID_72582240_3667_4063_1035_114677104388">
                            <UML:ModelElement.taggedValue>
                                <UML:TaggedValue tag="ea_type" value="Connector"/>
                                <UML:TaggedValue tag="direction" value="Source -&amp;gt; Destination"/>
                                <UML:TaggedValue tag="ea_sourceName" value="RIGHT"/>
                                <UML:TaggedValue tag="ea_targetName" value="BUS_IN"/>
                                <UML:TaggedValue tag="ea_sourceType" value="Port"/>
                                <UML:TaggedValue tag="ea_targetType" value="Port"/>
                            </UML:ModelElement.taggedValue>
                            <UML:Association.connection>
                                <UML:AssociationEnd type="EAID_62383181_5076_7775_6410_337631113190"/>
                                <UML:AssociationEnd type="EAID_64511351_7485_2307_3890_910827545249"/>
                            </UML:Association.connection>
                        </UML:Association>
                        <UML:Association xmi.id="EAID_62767209_9928_7175_4926_571305558582">
                            <UML:ModelElement.taggedValue>
                                <UML:TaggedValue tag="ea_type" value="Connector"/>
                                <UML:TaggedValue tag="direction" value="Source -&amp;gt; Destination"/>
                                <UML:TaggedValue tag="ea_sourceName" value="PILOT_FLYING"/>
                                <UML:TaggedValue tag="ea_targetName" value="RIGHT"/>
                                <UML:TaggedValue tag="ea_sourceType" value="Port"/>
                                <UML:TaggedValue tag="ea_targetType" value="Port"/>
                            </UML:ModelElement.taggedValue>
                            <UML:Association.connection>
                                <UML:AssociationEnd type="EAID_37758531_2478_7907_6323_354908967151"/>
                                <UML:AssociationEnd type="EAID_36587005_4617_2656_9841_664002452976"/>
                            </UML:Association.connection>
                        </UML:Association>
                        <UML:Association xmi.id="EAID_98117574_1701_1669_3598_295883956178">
                            <UML:ModelElement.taggedValue>
                                <UML:TaggedValue tag="ea_type" value="Connector"/>
                                <UML:TaggedValue tag="direction" value="Source -&amp;gt; Destination"/>
                                <UML:TaggedValue tag="ea_sourceName" value="TRANSFER_SWITCH"/>
                                <UML:TaggedValue tag="ea_targetName" value="TRANSFER_SWITCH"/>
                                <UML:TaggedValue tag="ea_sourceType" value="Port"/>
                                <UML:TaggedValue tag="ea_targetType" value="Port"/>
                            </UML:ModelElement.taggedValue>
                            <UML:Association.connection>
                                <UML:AssociationEnd type="EAID_62321814_7253_5752_8551_113955679121"/>
                                <UML:AssociationEnd type="EAID_27649737_4131_4757_6316_827709435040"/>
                            </UML:Association.connection>
                        </UML:Association>
                        <UML:Association xmi.id="EAID_72829152_2254_5948_5742_580064746375">
                            <UML:ModelElement.taggedValue>
                                <UML:TaggedValue tag="ea_type" value="Connector"/>
                                <UML:TaggedValue tag="direction" value="Source -&amp;gt; Destination"/>
                                <UML:TaggedValue tag="ea_sourceName" value="PRIMARY_SIDE"/>
                                <UML:TaggedValue tag="ea_targetName" value="PRIMARY_SIDE"/>
                                <UML:TaggedValue tag="ea_sourceType" value="Port"/>
                                <UML:TaggedValue tag="ea_targetType" value="Port"/>
                            </UML:ModelElement.taggedValue>
                            <UML:Association.connection>
                                <UML:AssociationEnd type="EAID_63056512_6562_9130_3480_502808193680"/>
                                <UML:AssociationEnd type="EAID_91752754_8824_1399_8305_902131435515"/>
                            </UML:Association.connection>
                        </UML:Association>
                        <UML:Association xmi.id="EAID_45526717_3513_7011_4834_576738817399">
                            <UML:ModelElement.taggedValue>
                                <UML:TaggedValue tag="ea_type" value="Connector"/>
                                <UML:TaggedValue tag="direction" value="Source -&amp;gt; Destination"/>
                                <UML:TaggedValue tag="ea_sourceName" value="TRANSFER_SWITCH"/>
                                <UML:TaggedValue tag="ea_targetName" value="TRANSFER_SWITCH"/>
                                <UML:TaggedValue tag="ea_sourceType" value="Port"/>
                                <UML:TaggedValue tag="ea_targetType" value="Port"/>
                            </UML:ModelElement.taggedValue>
                            <UML:Association.connection>
                                <UML:AssociationEnd type="EAID_62321814_7253_5752_8551_113955679121"/>
                                <UML:AssociationEnd type="EAID_69380472_2108_7027_4289_352595488414"/>
                            </UML:Association.connection>
                        </UML:Association>
                        <UML:Association xmi.id="EAID_34831690_8246_8549_3633_818792667636">
                            <UML:ModelElement.taggedValue>
                                <UML:TaggedValue tag="ea_type" value="Connector"/>
                                <UML:TaggedValue tag="direction" value="Source -&amp;gt; Destination"/>
                                <UML:TaggedValue tag="ea_sourceName" value="PRIMARY_SIDE"/>
                                <UML:TaggedValue tag="ea_targetName" value="PRIMARY_SIDE"/>
                                <UML:TaggedValue tag="ea_sourceType" value="Port"/>
                                <UML:TaggedValue tag="ea_targetType" value="Port"/>
                            </UML:ModelElement.taggedValue>
                            <UML:Association.connection>
                                <UML:AssociationEnd type="EAID_63056512_6562_9130_3480_502808193680"/>
                                <UML:AssociationEnd type="EAID_30392826_5149_2174_8662_132240733259"/>
                            </UML:Association.connection>
                        </UML:Association>
                    </UML:Namespace.ownedElement>
                </UML:Package>
            </UML:Namespace.ownedElement>
        </UML:Model>
        <UML:TaggedValue modelElement="EAID_42650654_9738_5473_4177_718982955281" tag="isEncapsulated" value="#NOTES#Values: true,false&amp;#10;" xmi.id="EAID_88223251_6924_7318_9563_642771790327"/>
        <UML:TaggedValue modelElement="EAID_47333264_1216_2617_4382_771395273610" tag="isEncapsulated" value="#NOTES#Values: true,false&amp;#10;" xmi.id="EAID_95597625_9940_6941_5038_503148575467"/>
        <UML:TaggedValue modelElement="EAID_92984298_1855_2127_1284_294648102216" tag="isEncapsulated" value="#NOTES#Values: true,false&amp;#10;" xmi.id="EAID_36808433_8207_3295_6545_451834682909"/>
        <UML:Diagram diagramType="ClassDiagram" name="One Level Block Hierarchy" owner="EAPK_30494558_2566_9176_5511_514611744827" toolName="Enterprise Architect 2.5" xmi.id="EAID_63249069_2572_2614_5583_421862587793">
            <UML:ModelElement.taggedValue>
                <UML:TaggedValue tag="package" value="EAPK_30494558_2566_9176_5511_514611744827"/>
                <UML:TaggedValue tag="styleex" value="MDGDgm=SysML1.4::BlockDefinition;SF=1;"/>
            </UML:ModelElement.taggedValue>
            <UML:Diagram.element>
                <UML:DiagramElement geometry="Left=60;Top=60;Right=180;Bottom=180;" subject="EAID_42650654_9738_5473_4177_718982955281"/>
                <UML:DiagramElement geometry="Left=60;Top=60;Right=180;Bottom=180;" subject="EAID_47333264_1216_2617_4382_771395273610"/>
                <UML:DiagramElement geometry="Left=60;Top=60;Right=180;Bottom=180;" subject="EAID_92984298_1855_2127_1284_294648102216"/>
                <UML:DiagramElement geometry="Left=60;Top=60;Right=160;Bottom=160;" subject="EAID_63056512_6562_9130_3480_502808193680"/>
                <UML:DiagramElement geometry="Left=60;Top=80;Right=160;Bottom=180;" subject="EAID_62321814_7253_5752_8551_113955679121"/>
                <UML:DiagramElement geometry="Left=60;Top=100;Right=160;Bottom=200;" subject="EAID_35789767_5738_6705_3211_666834836315"/>
                <UML:DiagramElement geometry="Left=60;Top=120;Right=160;Bottom=220;" subject="EAID_92402114_5900_9402_6879_646260384548"/>
                <UML:DiagramElement geometry="Left=60;Top=140;Right=160;Bottom=240;" subject="EAID_78492781_2296_5292_6326_969686845577"/>
                <UML:DiagramElement geometry="Left=60;Top=160;Right=160;Bottom=260;" subject="EAID_72550204_3615_8175_8303_354971874703"/>
                <UML:DiagramElement geometry="Left=60;Top=180;Right=160;Bottom=280;" subject="EAID_43633111_1320_2944_5067_705911547494"/>
                <UML:DiagramElement geometry="Left=60;Top=200;Right=160;Bottom=300;" subject="EAID_72721734_6950_2850_4835_415330318614"/>
                <UML:DiagramElement geometry="Left=60;Top=220;Right=160;Bottom=320;" subject="EAID_45157353_1566_9797_4543_452208450746"/>
                <UML:DiagramElement geometry="Left=60;Top=240;Right=160;Bottom=340;" subject="EAID_97287088_9646_9394_8128_536388273418"/>
            </UML:Diagram.element>
        </UML:Diagram>
        <UML:Diagram diagramType="CompositeStructureDiagram" name="FCS" owner="EAPK_30494558_2566_9176_5511_514611744827" toolName="Enterprise Architect 2.5" xmi.id="EAID_43130174_8573_8075_2473_503365140897">
            <UML:ModelElement.taggedValue>
                <UML:TaggedValue tag="package" value="EAPK_30494558_2566_9176_5511_514611744827"/>
                <UML:TaggedValue tag="type" value="CompositeStructure"/>
                <UML:TaggedValue tag="ea_localid" value="4"/>
                <UML:TaggedValue tag="parent" value="EAID_92984298_1855_2127_1284_294648102216"/>
                <UML:TaggedValue tag="styleex" value="MDGDgm=SysML1.4::InternalBlock;SF=1;"/>
            </UML:ModelElement.taggedValue>
            <UML:Diagram.element>
                <UML:DiagramElement geometry="Left=699;Top=129;Right=714;Bottom=144;" subject="EAID_63056512_6562_9130_3480_502808193680"/>
                <UML:DiagramElement geometry="Left=699;Top=129;Right=714;Bottom=144;" subject="EAID_62321814_7253_5752_8551_113955679121"/>
                <UML:DiagramElement geometry="Left=699;Top=129;Right=714;Bottom=144;" subject="EAID_47176645_1928_8006_5407_972225358555"/>
                <UML:DiagramElement geometry="Left=699;Top=129;Right=714;Bottom=144;" subject="EAID_62383181_5076_7775_6410_337631113190"/>
                <UML:DiagramElement geometry="Left=699;Top=129;Right=714;Bottom=144;" subject="EAID_44358266_6456_5713_4289_591841327278"/>
                <UML:DiagramElement geometry="Left=699;Top=129;Right=714;Bottom=144;" subject="EAID_43145413_8646_1839_4472_712471442927"/>
                <UML:DiagramElement geometry="Left=699;Top=129;Right=714;Bottom=144;" subject="EAID_16176098_5148_2296_2967_104075413716"/>
                <UML:DiagramElement geometry="Left=699;Top=129;Right=714;Bottom=144;" subject="EAID_36587005_4617_2656_9841_664002452976"/>
                <UML:DiagramElement geometry="Left=699;Top=129;Right=714;Bottom=144;" subject="EAID_86284156_2141_1349_5313_117505446321"/>
                <UML:DiagramElement geometry="Left=699;Top=129;Right=714;Bottom=144;" subject="EAID_86745649_2140_9766_7823_602554421163"/>
                <UML:DiagramElement geometry="Left=699;Top=129;Right=714;Bottom=144;" subject="EAID_18913292_7041_9246_3127_995479321146"/>
                <UML:DiagramElement geometry="Left=699;Top=129;Right=714;Bottom=144;" subject="EAID_64511351_7485_2307_3890_910827545249"/>
                <UML:DiagramElement geometry="Left=699;Top=129;Right=714;Bottom=144;" subject="EAID_82509287_3546_7046_7842_138363915121"/>
                <UML:DiagramElement geometry="Left=699;Top=129;Right=714;Bottom=144;" subject="EAID_37758531_2478_7907_6323_354908967151"/>
                <UML:DiagramElement geometry="Left=699;Top=129;Right=714;Bottom=144;" subject="EAID_30392826_5149_2174_8662_132240733259"/>
                <UML:DiagramElement geometry="Left=699;Top=129;Right=714;Bottom=144;" subject="EAID_69380472_2108_7027_4289_352595488414"/>
                <UML:DiagramElement geometry="Left=699;Top=129;Right=714;Bottom=144;" subject="EAID_12588843_2119_6794_9583_108364758766"/>
                <UML:DiagramElement geometry="Left=699;Top=129;Right=714;Bottom=144;" subject="EAID_26893162_1009_5954_2311_332999979623"/>
                <UML:DiagramElement geometry="Left=699;Top=129;Right=714;Bottom=144;" subject="EAID_40089394_1448_6739_5748_907946359794"/>
                <UML:DiagramElement geometry="Left=699;Top=129;Right=714;Bottom=144;" subject="EAID_12702060_6825_5470_5816_870500770863"/>
                <UML:DiagramElement geometry="Left=699;Top=129;Right=714;Bottom=144;" subject="EAID_91752754_8824_1399_8305_902131435515"/>
                <UML:DiagramElement geometry="Left=699;Top=129;Right=714;Bottom=144;" subject="EAID_27649737_4131_4757_6316_827709435040"/>
            </UML:Diagram.element>
        </UML:Diagram>
    </XMI.content>
    <XMI.difference/>
    <XMI.extensions xmi.extender="Enterprise Architect 2.5"/>
</XMI>
